{
    "01": 37.53,
    "02": 41.24,
    "03": 38.78,
    "04": 42.57,
    "phd_full": 90,
    "sla_embu_full": 95,
    "bonus_valido": false,
    "valor_bonus_contagem": 24.57,
    "phd_bonus_values": {
        "90": 0.0,
        "91": 49.15,
        "92": 98.3,
        "93": 147.45,
        "94": 196.6,
        "95": 245.75,
        "96": 294.9,
        "97": 344.05,
        "98": 393.2,
        "99": 442.35,
        "100": 491.5
    },
    "phd_mini_low": 90,
    "phd_mini_high": 91,
    "phd_decimal": 3.0000000000001137,
    "media": 40.03,
    "media_full": 90,
    "multiplicador_bonus_sla": 0.5,
    "porcentagem_da_barra_sla": 0,
    "porcentagem_da_barra_pdh_mini": 0,
    "porcentagem_da_barra_pdh_full": 0,
    "valor_bonus": 0.01,
    "pedidos_pendentes": 2747,
    "envios_dia": 1277,
    "envios_mes": 4915
}